libreriajuan/__init__.py
libreriajuan/elt.py
libreriajuan/srmd.py
libreriajuan-0.0.3.dist-info/METADATA
libreriajuan-0.0.3.dist-info/WHEEL
libreriajuan-0.0.3.dist-info/top_level.txt
libreriajuan-0.0.3.dist-info/RECORD
