Metadata-Version: 2.4
Name: libreriajuan
Version: 0.0.3
Summary: libreria para una calculadora simple de operaciones basicas, dimencionamieto electrico para instalacion de motores industriales
Author-email: Juan Alex Quispe Arce <juan19alex@gmail.com>
Classifier: Programming Language :: Python :: 3
Classifier: Operating System :: OS Independent
Requires-Python: >=3.9
